{
  "_type": "export",
  "__export_format": 4,
  "__export_date": "2023-04-03T22:00:37.647Z",
  "__export_source": "insomnia.desktop.app:v2022.7.5",
  "resources": [
    {
      "_id": "req_ec46490fe1cf4e7d861e395e055bfebb",
      "parentId": "fld_93171e120fc34f3f98f1d6944fec18db",
      "modified": 1680558752998,
      "created": 1680558330716,
      "url": "http://localhost:8081/api/books",
      "name": "/api/books BORRAR TODOS",
      "description": "",
      "method": "DELETE",
      "body": {},
      "parameters": [],
      "headers": [],
      "authentication": {},
      "metaSortKey": -1680558330716,
      "isPrivate": false,
      "settingStoreCookies": true,
      "settingSendCookies": true,
      "settingDisableRenderRequestBody": false,
      "settingEncodeUrl": true,
      "settingRebuildPath": true,
      "settingFollowRedirects": "global",
      "_type": "request"
    },
    {
      "_id": "fld_93171e120fc34f3f98f1d6944fec18db",
      "parentId": "wrk_fb9bffba812a4a9799bd6860c7672359",
      "modified": 1676975223415,
      "created": 1676975223415,
      "name": "OB Spring REST",
      "description": "",
      "environment": {},
      "environmentPropertyOrder": null,
      "metaSortKey": -1676975223415,
      "_type": "request_group"
    },
    {
      "_id": "wrk_fb9bffba812a4a9799bd6860c7672359",
      "parentId": null,
      "modified": 1672818845167,
      "created": 1672818845167,
      "name": "New Document",
      "description": "",
      "scope": "design",
      "_type": "workspace"
    },
    {
      "_id": "req_e1a72cb573264943b03db79060838501",
      "parentId": "fld_93171e120fc34f3f98f1d6944fec18db",
      "modified": 1680558857964,
      "created": 1680557346614,
      "url": "http://localhost:8081/api/books/1",
      "name": "/api/books/1 BORRAR UNO",
      "description": "",
      "method": "DELETE",
      "body": {},
      "parameters": [],
      "headers": [],
      "authentication": {},
      "metaSortKey": -1680557346614,
      "isPrivate": false,
      "settingStoreCookies": true,
      "settingSendCookies": true,
      "settingDisableRenderRequestBody": false,
      "settingEncodeUrl": true,
      "settingRebuildPath": true,
      "settingFollowRedirects": "global",
      "_type": "request"
    },
    {
      "_id": "req_0898721e000f454aad245529371d014f",
      "parentId": "fld_93171e120fc34f3f98f1d6944fec18db",
      "modified": 1680558782077,
      "created": 1680556589630,
      "url": "http://localhost:8081/api/books/",
      "name": "/api/books/ MODIFICAR",
      "description": "",
      "method": "PUT",
      "body": {
        "mimeType": "application/json",
        "text": "{\n\t\t\"id\": 1,\n\t\t\"title\": \"El llano en llamas actualizado en Insomnia\",\n\t\t\"author\": \"Juan Rulfo\",\n\t\t\"numPages\": 120,\n\t\t\"price\": 112.99,\n\t\t\"releaseDate\": \"1999-05-03\",\n\t\t\"online\": true\n\t}"
      },
      "parameters": [],
      "headers": [
        {
          "name": "Content-Type",
          "value": "application/json"
        }
      ],
      "authentication": {},
      "metaSortKey": -1680556589630,
      "isPrivate": false,
      "settingStoreCookies": true,
      "settingSendCookies": true,
      "settingDisableRenderRequestBody": false,
      "settingEncodeUrl": true,
      "settingRebuildPath": true,
      "settingFollowRedirects": "global",
      "_type": "request"
    },
    {
      "_id": "req_415446d968f747338ddc8fa3bd83af68",
      "parentId": "fld_93171e120fc34f3f98f1d6944fec18db",
      "modified": 1680558799545,
      "created": 1677029725980,
      "url": "http://localhost:8081/api/books/",
      "name": "/api/books/ BUSCAR TODOS",
      "description": "",
      "method": "GET",
      "body": {},
      "parameters": [],
      "headers": [],
      "authentication": {},
      "metaSortKey": -1677029725980,
      "isPrivate": false,
      "settingStoreCookies": true,
      "settingSendCookies": true,
      "settingDisableRenderRequestBody": false,
      "settingEncodeUrl": true,
      "settingRebuildPath": true,
      "settingFollowRedirects": "global",
      "_type": "request"
    },
    {
      "_id": "req_31fb0901c5d045a9bc29974affcceca2",
      "parentId": "fld_93171e120fc34f3f98f1d6944fec18db",
      "modified": 1680558809793,
      "created": 1677029011607,
      "url": "http://localhost:8081/api/books",
      "name": "/api/books CREAR",
      "description": "",
      "method": "POST",
      "body": {
        "mimeType": "application/json",
        "text": "{\n\t\"title\": \"Atomic Habits\",\n\t\"author\": \"James Clear\",\n\t\"numPages\": 340,\n\t\"price\": 399.99,\n\t\"releaseDate\": \"2010-09-13\",\n\t\"online\": true\n}"
      },
      "parameters": [],
      "headers": [
        {
          "name": "Content-Type",
          "value": "application/json",
          "id": "pair_0cbf58c1cf3a4862bc48cc4c42201461"
        }
      ],
      "authentication": {},
      "metaSortKey": -1677029011607,
      "isPrivate": false,
      "settingStoreCookies": true,
      "settingSendCookies": true,
      "settingDisableRenderRequestBody": false,
      "settingEncodeUrl": true,
      "settingRebuildPath": true,
      "settingFollowRedirects": "global",
      "_type": "request"
    },
    {
      "_id": "req_da219a3265ed4795873c7169cc822f9e",
      "parentId": "fld_93171e120fc34f3f98f1d6944fec18db",
      "modified": 1680558839941,
      "created": 1677028017604,
      "url": "http://localhost:8081/api/books/2",
      "name": "/api/books/1 BUSCAR UNO",
      "description": "",
      "method": "GET",
      "body": {},
      "parameters": [],
      "headers": [],
      "authentication": {},
      "metaSortKey": -1677028017604,
      "isPrivate": false,
      "settingStoreCookies": true,
      "settingSendCookies": true,
      "settingDisableRenderRequestBody": false,
      "settingEncodeUrl": true,
      "settingRebuildPath": true,
      "settingFollowRedirects": "global",
      "_type": "request"
    },
    {
      "_id": "req_e0805a7e0cae45f3886f2549c3b1e116",
      "parentId": "fld_93171e120fc34f3f98f1d6944fec18db",
      "modified": 1676977163066,
      "created": 1676975233086,
      "url": "http://localhost:8081/hola",
      "name": "/hola",
      "description": "",
      "method": "GET",
      "body": {},
      "parameters": [],
      "headers": [],
      "authentication": {},
      "metaSortKey": -1676975233086,
      "isPrivate": false,
      "settingStoreCookies": true,
      "settingSendCookies": true,
      "settingDisableRenderRequestBody": false,
      "settingEncodeUrl": true,
      "settingRebuildPath": true,
      "settingFollowRedirects": "global",
      "_type": "request"
    },
    {
      "_id": "env_41ea74c903aa8ecf24a6dbc46bc03df55456fccc",
      "parentId": "wrk_fb9bffba812a4a9799bd6860c7672359",
      "modified": 1672818845171,
      "created": 1672818845171,
      "name": "Base Environment",
      "data": {},
      "dataPropertyOrder": null,
      "color": null,
      "isPrivate": false,
      "metaSortKey": 1672818845171,
      "_type": "environment"
    },
    {
      "_id": "jar_41ea74c903aa8ecf24a6dbc46bc03df55456fccc",
      "parentId": "wrk_fb9bffba812a4a9799bd6860c7672359",
      "modified": 1672818845173,
      "created": 1672818845173,
      "name": "Default Jar",
      "cookies": [],
      "_type": "cookie_jar"
    },
    {
      "_id": "spc_f041207da46a423fadc0de05e24e99f3",
      "parentId": "wrk_fb9bffba812a4a9799bd6860c7672359",
      "modified": 1680555515992,
      "created": 1672818845168,
      "fileName": "New Document",
      "contents": "",
      "contentType": "yaml",
      "_type": "api_spec"
    },
    {
      "_id": "uts_6c74dc5dc91e46cfba1ee58f5c87a16d",
      "parentId": "wrk_fb9bffba812a4a9799bd6860c7672359",
      "modified": 1672818845178,
      "created": 1672818845178,
      "name": "Example Test Suite",
      "_type": "unit_test_suite"
    }
  ]
}